<?xml version="1.0" encoding="UTF-8" ?>
<feedback>
	<version>1.0</version>
	<report_metadata>
		<org_name>comcast.net</org_name>
		<email>dmarc-admin@alerts.comcast.net</email>
		<report_id>v2-1767236909-secure.200permits.com</report_id>
		<date_range>
			<begin>1767139200</begin>
			<end>1767225600</end>
		</date_range>
	</report_metadata>
	<policy_published>
		<domain>secure.200permits.com</domain>
		<adkim>s</adkim>
		<aspf>s</aspf>
		<p>reject</p>
		<sp>reject</sp>
		<pct>100</pct>
		<fo>0</fo>
	</policy_published>
	<record>
		<row>
			<source_ip>52.4.242.136</source_ip>
			<count>2</count>
			<policy_evaluated>
				<disposition>none</disposition>
				<dkim>pass</dkim>
				<spf>pass</spf>
			</policy_evaluated>
		</row>
		<identifiers>
			<header_from>secure.200permits.com</header_from>
			<envelope_from>secure.200permits.com</envelope_from>
		</identifiers>
		<auth_results>
			<dkim>
				<domain>secure.200permits.com</domain>
				<result>pass</result>
				<selector>default</selector>
			</dkim>
			<spf>
				<domain>secure.200permits.com</domain>
				<scope>mfrom</scope>
				<result>pass</result>
			</spf>
		</auth_results>
	</record>
</feedback>
